uniprop.cp39-win32.pyd
uniprop-1.7.dist-info/LICENSE
uniprop-1.7.dist-info/METADATA
uniprop-1.7.dist-info/WHEEL
uniprop-1.7.dist-info/top_level.txt
uniprop-1.7.dist-info/RECORD
