Metadata-Version: 2.1
Name: uniprop
Version: 1.7
Summary: 'uniprop' provides the Unicode properties of codepoints similar to those of the unicodedata module.
Home-page: https://bitbucket.org/mrabarnett/uniprop
Author: Matthew Barnett
Author-email: uniprop@mrabarnett.plus.com
License: Apache Software License
Platform: UNKNOWN
Classifier: Development Status :: 5 - Production/Stable
Classifier: Intended Audience :: Developers
Classifier: Programming Language :: Python :: 3.9
Classifier: Operating System :: OS Independent
Classifier: Topic :: Scientific/Engineering :: Information Analysis
Classifier: Topic :: Software Development :: Libraries :: Python Modules
Classifier: Topic :: Text Processing
Classifier: Topic :: Text Processing :: General
Classifier: License :: OSI Approved :: Apache Software License
Requires-Python: >=3.6
License-File: LICENSE
